{
    "connector": {
        "type": "simple_rest",
        "format": "csv",
        "refreshInterval": 86400,
        "props": {
            "endpoint_url": "http://api.semrush.com/?type=domain_organic&key=<yourAPIKey>&export_columns=Ph,Po,Pp,Pd,Nq,Cp,Ur,Tr,Tc,Co,Nr,Td&domain=<yourDomain>&display_sort=tr_desc&database=<yourRegionalDatabase>&display_limit=5",
            "method": "get"
        }
    }
}
// "name": "SEMRush Top 5 Keywords",
// "description": "Obtain top 5 keywords for the specified domain. Originates from the Gallery.",